lab1_macos/src/ALU_Template.v
`timescale 1ns / 100ps

module ALU 
(
	input   wire    [15:0]          A_i,
	input   wire    [15:0]          B_i,
	input   wire    [3:0]           OP_i,
	input   wire                    C_i,
	
	output  wire     [15:0]         F_o,
	output  wire                    C_o
);
	
	// TODO : If your module and its pin have different OP_CODE, you should change the mapping.
	localparam  OP_ADD  = 4'b0000,
				OP_SUB  = 4'b0001,
				OP_ID   = 4'b1000,
				OP_NAND = 4'b1001, 
				OP_NOR  = 4'b1010,
				OP_XNOR = 4'b1011,
				OP_NOT  = 4'b1100,
				OP_AND  = 4'b1101, 
				OP_OR   = 4'b1110,
				OP_XOR  = 4'b1111,
				OP_LRS  = 4'b0010,
				OP_ARS  = 4'b0100,
				OP_RR   = 4'b0110,
				OP_LLS  = 4'b0011,
				OP_ALS  = 4'b0101,
				OP_RL   = 4'b0111;
	
	
	// TODO: Implement ALU


endmodule

Lab1/src/ALU_TB.v
`timescale 100ps / 100ps

// OP CODE
// TODO : If your module and its pin have different OP_CODE, you should change the mapping.

// Arithmetic
`define	OP_ADD	    4'b0000
`define	OP_SUB	    4'b0001
//  Bitwise Boolean operation
`define	OP_ID		4'b1000
`define	OP_NAND	    4'b1001
`define	OP_NOR      4'b1010
`define	OP_XNOR     4'b1011
`define	OP_NOT      4'b1100
`define	OP_AND      4'b1101
`define	OP_OR		4'b1110
`define	OP_XOR      4'b1111
// Shifting
`define	OP_LRS      4'b0010
`define	OP_ARS      4'b0100
`define	OP_RR       4'b0110
`define	OP_LLS      4'b0011
`define	OP_ALS      4'b0101
`define	OP_RL       4'b0111

module ALU_TB;

//Internal signals declarations:
	reg     [15:0]  A_i;
	reg     [15:0]  B_i;
	reg     [3:0]   OP_i;
	reg             C_i;
	
	wire    [15:0]  F_o;
	wire            C_o;

	reg     [15:0]  Passed;
	reg     [15:0]  Failed;

// Unit Under Test port map
// TODO : If your module and its pin have different name, you should change the mapping.
	ALU UUT (
		.A_i        (A_i),
		.B_i        (B_i),
		.OP_i       (OP_i),
		.C_i        (C_i),
		.F_o        (F_o),
		.C_o        (C_o)
	);

initial begin
	Passed = 0;
	Failed = 0;

	$dumpfile("vcd/ALU_TB.vcd");
	$dumpvars(0, ALU_TB);
	
	ArithmeticTest;
	BitwiseBooleanTest;
	ShiftingTest;
	
	$display("Passed = %0d, Failed = %0d", Passed, Failed);	
	$finish;
end

task ArithmeticTest;
begin
	AddTest;
	SubTest;
end
endtask					 

task BitwiseBooleanTest;
begin
	IdTest;
	NandTest;
	NorTest;
	XnorTest;
	NotTest;
	AndTest;
	OrTest;
	XorTest;
end
endtask

task ShiftingTest;
begin
	LrsTest;
	ArsTest;
	RrTest;
	LlsTest;
	AlsTest;
	RlTest;
end
endtask

task AddTest;
begin
	OP_i = `OP_ADD;
	
	Test("Add-1", 0, 0, 0, 0, 0);
	Test("Add-2", 0, 0, 1, 1, 0);
	Test("Add-3", 2, 3, 0, 5, 0);
	Test("Add-4", 3, 2, 0, 5, 0);
	Test("Add-5", 2, 3, 1, 6, 0);
	Test("Add-6", 3, 2, 1, 6, 0);
	Test("Add-7", 16'h8000, 16'h8000, 0, 0, 1);
	Test("Add-8", 16'hffff, 1, 0, 0, 1);
	Test("Add-9", 16'hffff, 16'hffff, 0, 16'hfffe, 1);
end
endtask

task SubTest;
begin
	OP_i = `OP_SUB;
	
	Test("Sub-1", 0, 0, 0, 0, 0);
	Test("Sub-2", 1, 0, 0, 1, 0);
	Test("Sub-3", 0, 1, 0, 16'hffff, 1);
	Test("Sub-4", 0, 0, 1, 16'hffff, 1);
	Test("Sub-5", 3, 2, 0, 1, 0);
	Test("Sub-6", 3, 2, 1, 0, 0);
	Test("Sub-7", 0, 16'hffff, 1, 0, 1);
end
endtask		  

task IdTest;
begin
	OP_i = `OP_ID;
	
	Test("Id-1", 0, 0, 0, 0, 0);
	Test("Id-2", 1, 0, 0, 1, 0);
	Test("Id-3", 16'habcd, 0, 0, 16'habcd, 0);
end
endtask

task NandTest;
begin
	OP_i = `OP_NAND;												 
	
	Test("Nand-1", {4{4'b0011}}, {4{4'b0101}}, 0, {4{4'b1110}}, 0);
	Test("Nand-2", {4{4'b1100}}, {4{4'b0101}}, 0, {4{4'b1011}}, 0); 
end
endtask

task NorTest;
begin
	OP_i = `OP_NOR;												 
	
	Test("Nor-1", {4{4'b0011}}, {4{4'b0101}}, 0, {4{4'b1000}}, 0);
	Test("Nor-2", {4{4'b1100}}, {4{4'b0101}}, 0, {4{4'b0010}}, 0);
end
endtask

task XnorTest;
begin
	OP_i = `OP_XNOR;												 
	
	Test("Xnor-1", {4{4'b0011}}, {4{4'b0101}}, 0, {4{4'b1001}}, 0);
	Test("Xnor-2", {4{4'b1100}}, {4{4'b0101}}, 0, {4{4'b0110}}, 0);
end
endtask

task NotTest;
begin
	OP_i = `OP_NOT;
		
	Test("Not-1", 0, 0, 0, 16'hffff, 0);
	Test("Not-2", 1, 0, 0, 16'hfffe, 0);
	Test("Not-3", 16'habcd, 0, 0, 16'h5432, 0);
end
endtask

task AndTest;
begin
	OP_i = `OP_AND;												 
		
	Test("And-1", {4{4'b0011}}, {4{4'b0101}}, 0, {4{4'b0001}}, 0);
	Test("And-2", {4{4'b1100}}, {4{4'b0101}}, 0, {4{4'b0100}}, 0);
end
endtask

task OrTest;
begin
	OP_i = `OP_OR;												 
		
	Test("Or-1", {4{4'b0011}}, {4{4'b0101}}, 0, {4{4'b0111}}, 0);
	Test("Or-2", {4{4'b1100}}, {4{4'b0101}}, 0, {4{4'b1101}}, 0);
end
endtask

task XorTest;
begin
	OP_i = `OP_XOR;												 
		
	Test("Xor-1", {4{4'b0011}}, {4{4'b0101}}, 0, {4{4'b0110}}, 0);
	Test("Xor-2", {4{4'b1100}}, {4{4'b0101}}, 0, {4{4'b1001}}, 0);
end
endtask

task LrsTest;
begin
	OP_i = `OP_LRS;
		
	Test("Lrs-1", 16'ha, 0, 0, 5, 0);
	Test("Lrs-2", 1, 0, 0, 0, 0);
	Test("Lrs-3", 16'hfffa, 0, 0, 16'h7ffd, 0);
	Test("Lrs-4", 16'hffff, 0, 0, 16'h7fff, 0);
end
endtask

task ArsTest;
begin
	OP_i = `OP_ARS;
		
	Test("Ars-1", 16'ha, 0, 0, 5, 0);
	Test("Ars-2", 1, 0, 0, 0, 0);
	Test("Ars-3", 16'hfffa, 0, 0, 16'hfffd, 0);
	Test("Ars-4", 16'hffff, 0, 0, 16'hffff, 0);
end
endtask

task RrTest;
begin
	OP_i = `OP_RR;
		
	Test("Rr-1", 16'ha, 0, 0, 16'h5, 0);
	Test("Rr-2", 16'hb, 0, 0, 16'h8005, 0);
end
endtask

task LlsTest;
	begin
	OP_i = `OP_LLS;
		
	Test("Lls-1", 16'ha, 0, 0, 16'h14, 0);
	Test("Lls-2", 16'hf000, 0, 0, 16'he000, 0);
end
endtask

task AlsTest;
begin
	OP_i = `OP_ALS;
		
	Test("Als-1", 16'ha, 0, 0, 16'h14, 0);
	Test("Als-2", 16'hf000, 0, 0, 16'he000, 0);
end
endtask

task RlTest;
begin
	OP_i = `OP_RL;
		
	Test("Rl-1", 16'h7000, 0, 0, 16'he000, 0);
	Test("Rl-2", 16'hf000, 0, 0, 16'he001, 0);
end
endtask

task Test; 
	input   [16 * 8 : 0]    Testname;
	input   [15:0]          A_;
	input   [15:0]          B_;
	input                   Cin_;
	input   [15:0]          F_expected;
	input                   Cout_expected;  
begin
	$display("TEST %s :", Testname);
	A_i = A_;
	B_i = B_;
	C_i = Cin_;
	#1;
	if (F_o == F_expected && C_o == Cout_expected) begin
		$display("PASSED\n");
		Passed = Passed + 1;
	end
	else begin
		$display("FAILED");
		$display("A = %0b, B = %0b, Cin = %0b, F = %0b (Ans : %0b), Cout = %0b (Ans : %0b)\n", A_, B_, Cin_, F_o, F_expected, C_o, Cout_expected);
		Failed = Failed + 1;
	end
end
endtask

endmodule

lab1_macos/vcd/ALU_TB.vcd
$date
	Wed Sep  9 00:03:16 2026
$end
$version
	Icarus Verilog
$end
$timescale
	100ps
$end
$scope module ALU_TB $end
$var wire 1 ! C_o $end
$var wire 16 " F_o [15:0] $end
$var reg 16 # A_i [15:0] $end
$var reg 16 $ B_i [15:0] $end
$var reg 1 % C_i $end
$var reg 16 & Failed [15:0] $end
$var reg 4 ' OP_i [3:0] $end
$var reg 16 ( Passed [15:0] $end
$scope module UUT $end
$var wire 16 ) A_i [15:0] $end
$var wire 16 * B_i [15:0] $end
$var wire 1 % C_i $end
$var wire 1 ! C_o $end
$var wire 16 + F_o [15:0] $end
$var wire 4 , OP_i [3:0] $end
$var parameter 4 - OP_ADD $end
$var parameter 4 . OP_ALS $end
$var parameter 4 / OP_AND $end
$var parameter 4 0 OP_ARS $end
$var parameter 4 1 OP_ID $end
$var parameter 4 2 OP_LLS $end
$var parameter 4 3 OP_LRS $end
$var parameter 4 4 OP_NAND $end
$var parameter 4 5 OP_NOR $end
$var parameter 4 6 OP_NOT $end
$var parameter 4 7 OP_OR $end
$var parameter 4 8 OP_RL $end
$var parameter 4 9 OP_RR $end
$var parameter 4 : OP_SUB $end
$var parameter 4 ; OP_XNOR $end
$var parameter 4 < OP_XOR $end
$upscope $end
$scope task AddTest $end
$upscope $end
$scope task AlsTest $end
$upscope $end
$scope task AndTest $end
$upscope $end
$scope task ArithmeticTest $end
$upscope $end
$scope task ArsTest $end
$upscope $end
$scope task BitwiseBooleanTest $end
$upscope $end
$scope task IdTest $end
$upscope $end
$scope task LlsTest $end
$upscope $end
$scope task LrsTest $end
$upscope $end
$scope task NandTest $end
$upscope $end
$scope task NorTest $end
$upscope $end
$scope task NotTest $end
$upscope $end
$scope task OrTest $end
$upscope $end
$scope task RlTest $end
$upscope $end
$scope task RrTest $end
$upscope $end
$scope task ShiftingTest $end
$upscope $end
$scope task SubTest $end
$upscope $end
$scope task Test $end
$var reg 16 = A_ [15:0] $end
$var reg 16 > B_ [15:0] $end
$var reg 1 ? Cin_ $end
$var reg 1 @ Cout_expected $end
$var reg 16 A F_expected [15:0] $end
$var reg 129 B Testname [128:0] $end
$upscope $end
$scope task XnorTest $end
$upscope $end
$scope task XorTest $end
$upscope $end
$upscope $end
$enddefinitions $end
$comment Show the parameter values. $end
$dumpall
b1111 <
b1011 ;
b1 :
b110 9
b111 8
b1110 7
b1100 6
b1010 5
b1001 4
b10 3
b11 2
b1000 1
b100 0
b1101 /
b101 .
b0 -
$end
#0
$dumpvars
b100000101100100011001000010110100110001 B
b0 A
0@
0?
b0 >
b0 =
b0 ,
bz +
b0 *
b0 )
b0 (
b0 '
b0 &
0%
b0 $
b0 #
bz "
z!
$end
#1
1%
b1 A
1?
b100000101100100011001000010110100110010 B
b1 &
#2
0%
b11 $
b11 *
b10 #
b10 )
b101 A
0?
b11 >
b10 =
b100000101100100011001000010110100110011 B
b10 &
#3
b10 $
b10 *
b11 #
b11 )
b10 >
b11 =
b100000101100100011001000010110100110100 B
b11 &
#4
1%
b11 $
b11 *
b10 #
b10 )
b110 A
1?
b11 >
b10 =
b100000101100100011001000010110100110101 B
b100 &
#5
b10 $
b10 *
b11 #
b11 )
b10 >
b11 =
b100000101100100011001000010110100110110 B
b101 &
#6
0%
b1000000000000000 $
b1000000000000000 *
b1000000000000000 #
b1000000000000000 )
1@
b0 A
0?
b1000000000000000 >
b1000000000000000 =
b100000101100100011001000010110100110111 B
b110 &
#7
b1 $
b1 *
b1111111111111111 #
b1111111111111111 )
b1 >
b1111111111111111 =
b100000101100100011001000010110100111000 B
b111 &
#8
b1111111111111111 $
b1111111111111111 *
b1111111111111110 A
b1111111111111111 >
b100000101100100011001000010110100111001 B
b1000 &
#9
b0 $
b0 *
b0 #
b0 )
0@
b0 A
b0 >
b0 =
b101001101110101011000100010110100110001 B
b1 '
b1 ,
b1001 &
#10
b1 #
b1 )
b1 A
b1 =
b101001101110101011000100010110100110010 B
b1010 &
#11
b1 $
b1 *
b0 #
b0 )
1@
b1111111111111111 A
b1 >
b0 =
b101001101110101011000100010110100110011 B
b1011 &
#12
1%
b0 $
b0 *
1?
b0 >
b101001101110101011000100010110100110100 B
b1100 &
#13
0%
b10 $
b10 *
b11 #
b11 )
0@
b1 A
0?
b10 >
b11 =
b101001101110101011000100010110100110101 B
b1101 &
#14
1%
b0 A
1?
b101001101110101011000100010110100110110 B
b1110 &
#15
b1111111111111111 $
b1111111111111111 *
b0 #
b0 )
1@
b1111111111111111 >
b0 =
b101001101110101011000100010110100110111 B
b1111 &
#16
0%
b0 $
b0 *
0@
0?
b0 >
b1001001011001000010110100110001 B
b1000 '
b1000 ,
b10000 &
#17
b1 #
b1 )
b1 A
b1 =
b1001001011001000010110100110010 B
b10001 &
#18
b1010101111001101 #
b1010101111001101 )
b1010101111001101 A
b1010101111001101 =
b1001001011001000010110100110011 B
b10010 &
#19
b101010101010101 $
b101010101010101 *
b11001100110011 #
b11001100110011 )
b1110111011101110 A
b101010101010101 >
b11001100110011 =
b10011100110000101101110011001000010110100110001 B
b1001 '
b1001 ,
b10011 &
#20
b1100110011001100 #
b1100110011001100 )
b1011101110111011 A
b1100110011001100 =
b10011100110000101101110011001000010110100110010 B
b10100 &
#21
b11001100110011 #
b11001100110011 )
b1000100010001000 A
b11001100110011 =
b100111001101111011100100010110100110001 B
b1010 '
b1010 ,
b10101 &
#22
b1100110011001100 #
b1100110011001100 )
b10001000100010 A
b1100110011001100 =
b100111001101111011100100010110100110010 B
b10110 &
#23
b11001100110011 #
b11001100110011 )
b1001100110011001 A
b11001100110011 =
b10110000110111001101111011100100010110100110001 B
b1011 '
b1011 ,
b10111 &
#24
b1100110011001100 #
b1100110011001100 )
b110011001100110 A
b1100110011001100 =
b10110000110111001101111011100100010110100110010 B
b11000 &
#25
b0 $
b0 *
b0 #
b0 )
b1111111111111111 A
b0 >
b0 =
b100111001101111011101000010110100110001 B
b1100 '
b1100 ,
b11001 &
#26
b1 #
b1 )
b1111111111111110 A
b1 =
b100111001101111011101000010110100110010 B
b11010 &
#27
b1010101111001101 #
b1010101111001101 )
b101010000110010 A
b1010101111001101 =
b100111001101111011101000010110100110011 B
b11011 &
#28
b101010101010101 $
b101010101010101 *
b11001100110011 #
b11001100110011 )
b1000100010001 A
b101010101010101 >
b11001100110011 =
b100000101101110011001000010110100110001 B
b1101 '
b1101 ,
b11100 &
#29
b1100110011001100 #
b1100110011001100 )
b100010001000100 A
b1100110011001100 =
b100000101101110011001000010110100110010 B
b11101 &
#30
b11001100110011 #
b11001100110011 )
b111011101110111 A
b11001100110011 =
b1001111011100100010110100110001 B
b1110 '
b1110 ,
b11110 &
#31
b1100110011001100 #
b1100110011001100 )
b1101110111011101 A
b1100110011001100 =
b1001111011100100010110100110010 B
b11111 &
#32
b11001100110011 #
b11001100110011 )
b110011001100110 A
b11001100110011 =
b101100001101111011100100010110100110001 B
b1111 '
b1111 ,
b100000 &
#33
b1100110011001100 #
b1100110011001100 )
b1001100110011001 A
b1100110011001100 =
b101100001101111011100100010110100110010 B
b100001 &
#34
b0 $
b0 *
b1010 #
b1010 )
b101 A
b0 >
b1010 =
b100110001110010011100110010110100110001 B
b10 '
b10 ,
b100010 &
#35
b1 #
b1 )
b0 A
b1 =
b100110001110010011100110010110100110010 B
b100011 &
#36
b1111111111111010 #
b1111111111111010 )
b111111111111101 A
b1111111111111010 =
b100110001110010011100110010110100110011 B
b100100 &
#37
b1111111111111111 #
b1111111111111111 )
b111111111111111 A
b1111111111111111 =
b100110001110010011100110010110100110100 B
b100101 &
#38
b1010 #
b1010 )
b101 A
b1010 =
b100000101110010011100110010110100110001 B
b100 '
b100 ,
b100110 &
#39
b1 #
b1 )
b0 A
b1 =
b100000101110010011100110010110100110010 B
b100111 &
#40
b1111111111111010 #
b1111111111111010 )
b1111111111111101 A
b1111111111111010 =
b100000101110010011100110010110100110011 B
b101000 &
#41
b1111111111111111 #
b1111111111111111 )
b1111111111111111 A
b1111111111111111 =
b100000101110010011100110010110100110100 B
b101001 &
#42
b1010 #
b1010 )
b101 A
b1010 =
b1010010011100100010110100110001 B
b110 '
b110 ,
b101010 &
#43
b1011 #
b1011 )
b1000000000000101 A
b1011 =
b1010010011100100010110100110010 B
b101011 &
#44
b1010 #
b1010 )
b10100 A
b1010 =
b100110001101100011100110010110100110001 B
b11 '
b11 ,
b101100 &
#45
b1111000000000000 #
b1111000000000000 )
b1110000000000000 A
b1111000000000000 =
b100110001101100011100110010110100110010 B
b101101 &
#46
b1010 #
b1010 )
b10100 A
b1010 =
b100000101101100011100110010110100110001 B
b101 '
b101 ,
b101110 &
#47
b1111000000000000 #
b1111000000000000 )
b1110000000000000 A
b1111000000000000 =
b100000101101100011100110010110100110010 B
b101111 &
#48
b111000000000000 #
b111000000000000 )
b111000000000000 =
b1010010011011000010110100110001 B
b111 '
b111 ,
b110000 &
#49
b1111000000000000 #
b1111000000000000 )
b1110000000000001 A
b1111000000000000 =
b1010010011011000010110100110010 B
b110001 &
#50
b110010 &
